auditor/__init__.py
auditor/assets/data/snips_dataset_dev.csv
auditor/assets/data/snips_dataset_test.csv
auditor/assets/data/snips_dataset_train.csv
auditor/evaluation/__init__.py
auditor/evaluation/discriminative.py
auditor/evaluation/evaluate.py
auditor/evaluation/expected_behavior.py
auditor/evaluation/generative.py
auditor/generations/__init__.py
auditor/generations/paraphrase.py
auditor/perturbations/__init__.py
auditor/perturbations/base.py
auditor/perturbations/constants.py
auditor/perturbations/paraphrase.py
auditor/perturbations/text.py
auditor/reporting/__init__.py
auditor/reporting/generate.py
auditor/reporting/templates/report_template.html
auditor/utils/__init__.py
auditor/utils/data.py
auditor/utils/dataset.py
auditor/utils/format.py
auditor/utils/logging.py
auditor/utils/misc.py
auditor/utils/progress_logger.py
auditor/utils/similarity.py
fiddler_auditor-0.0.5.dist-info/LICENSE
fiddler_auditor-0.0.5.dist-info/METADATA
fiddler_auditor-0.0.5.dist-info/WHEEL
fiddler_auditor-0.0.5.dist-info/top_level.txt
fiddler_auditor-0.0.5.dist-info/RECORD
