Metadata-Version: 2.1
Name: fiddler-auditor
Version: 0.0.5
Summary: Auditing large language models made easy.
Author-email: Fiddler Labs <support@fiddler.ai>
License: Elastic License 2.0 (ELv2)
Project-URL: repository, https://github.com/fiddler-labs/fiddler-auditor
Classifier: Programming Language :: Python :: 3
Classifier: Operating System :: OS Independent
Requires-Python: <4.0,>=3.8.1
License-File: LICENSE
Requires-Dist: notebook >=6.0.1
Requires-Dist: fiddler-checklist ==0.0.1
Requires-Dist: pandas <2.0,>=1.3.5
Requires-Dist: spacy-transformers >=1.1.8
Requires-Dist: jinja2 ==3.1.2
Requires-Dist: langchain <=0.0.330,>=0.0.158
Requires-Dist: openai <=0.28.1,>=0.27.0
Requires-Dist: sentence-transformers >=2.2.2
Requires-Dist: tqdm >=4.66.1
Requires-Dist: httplib2 ~=0.22.0
Provides-Extra: test
Requires-Dist: pytest ; extra == 'test'
Requires-Dist: build ; extra == 'test'
Requires-Dist: twine ; extra == 'test'
Requires-Dist: flake8 ; extra == 'test'
